xray_node/__init__.py
xray_node/main.py
xray_node/utils/__init__.py
xray_node/utils/consts.py
xray_node/utils/http.py
xray_node/utils/install.py
xray_node-0.0.1.dist-info/entry_points.txt
xray_node-0.0.1.dist-info/LICENSE
xray_node-0.0.1.dist-info/WHEEL
xray_node-0.0.1.dist-info/METADATA
xray_node-0.0.1.dist-info/RECORD
