Metadata-Version: 2.1
Name: xray-node
Version: 0.0.1
Summary: 
License: AGPLv3
Author: laoshan-taoist
Author-email: 65347330+laoshan-taoist@users.noreply.github.com
Requires-Python: >=3.8,<4.0
Classifier: License :: Other/Proprietary License
Classifier: Programming Language :: Python :: 3
Classifier: Programming Language :: Python :: 3.8
Classifier: Programming Language :: Python :: 3.9
Requires-Dist: click (>=7.1.2,<8.0.0)
Requires-Dist: httpx (>=0.17.1,<0.18.0)
